{
  "resourceType": "StructureDefinition",
  "id": "dapl-servicerequest",
  "meta": {
    "versionId": "12",
    "lastUpdated": "2026-03-27T02:03:11.293+00:00"
  },
  "extension": [
    {
      "url": "http://hl7.org/fhir/StructureDefinition/structuredefinition-wg",
      "valueCode": "cgp"
    },
    {
      "url": "http://hl7.org/fhir/StructureDefinition/structuredefinition-fmm",
      "valueInteger": 2,
      "_valueInteger": {
        "extension": [
          {
            "url": "http://hl7.org/fhir/StructureDefinition/structuredefinition-conformance-derivedFrom",
            "valueCanonical": "http://hl7.org/fhir/us/dapl/ImplementationGuide/dapl"
          }
        ]
      }
    },
    {
      "url": "http://hl7.org/fhir/StructureDefinition/structuredefinition-standards-status",
      "valueCode": "trial-use",
      "_valueCode": {
        "extension": [
          {
            "url": "http://hl7.org/fhir/StructureDefinition/structuredefinition-conformance-derivedFrom",
            "valueCanonical": "http://hl7.org/fhir/us/dapl/ImplementationGuide/dapl"
          }
        ]
      }
    }
  ],
  "url": "http://hl7.org/fhir/us/dapl/StructureDefinition/dapl-servicerequest",
  "version": "1.0.0-ballot",
  "name": "DAPLServiceRequest",
  "title": "DAPL ServiceRequest",
  "status": "active",
  "experimental": false,
  "date": "2026-05-08T05:01:52+10:00",
  "publisher": "HL7 International / Cross-Group Projects",
  "contact": [
    {
      "telecom": [
        {
          "system": "url",
          "value": "http://www.hl7.org/Special/committees/cgp"
        }
      ]
    }
  ],
  "description": "The DAPL profile establishes the core elements, extensions, vocabularies and value sets for representing deidentified and anonymized ServiceRequest.",
  "jurisdiction": [
    {
      "coding": [
        {
          "system": "urn:iso:std:iso:3166",
          "code": "US"
        }
      ]
    }
  ],
  "fhirVersion": "4.0.1",
  "mapping": [
    {
      "identity": "workflow",
      "uri": "http://hl7.org/fhir/workflow",
      "name": "Workflow Pattern"
    },
    {
      "identity": "v2",
      "uri": "http://hl7.org/v2",
      "name": "HL7 v2 Mapping"
    },
    {
      "identity": "rim",
      "uri": "http://hl7.org/v3",
      "name": "RIM Mapping"
    },
    {
      "identity": "w5",
      "uri": "http://hl7.org/fhir/fivews",
      "name": "FiveWs Pattern Mapping"
    },
    {
      "identity": "quick",
      "uri": "http://siframework.org/cqf",
      "name": "Quality Improvement and Clinical Knowledge (QUICK)"
    }
  ],
  "kind": "resource",
  "abstract": false,
  "type": "ServiceRequest",
  "baseDefinition": "http://hl7.org/fhir/StructureDefinition/ServiceRequest",
  "derivation": "constraint",
  "differential": {
    "element": [
      {
        "id": "ServiceRequest",
        "path": "ServiceRequest",
        "short": "DAPL ServiceRequest",
        "definition": "The DAPL profile establishes the core elements, extensions, vocabularies and value sets for representing deidentified and anonymized ServiceRequests."
      },
      {
        "id": "ServiceRequest.id",
        "path": "ServiceRequest.id",
        "short": "The ServiceRequest identifier created by the DARTS services potentially linked back to the original ServiceRequest as needed.",
        "definition": "DARTS ServiceRequest resource identifier.",
        "mustSupport": true
      },
      {
        "id": "ServiceRequest.text",
        "path": "ServiceRequest.text",
        "short": "Cannot include any text in the resource as part of the de-identified or anonymized data.",
        "min": 0,
        "max": "0",
        "mustSupport": false
      },
      {
        "id": "ServiceRequest.contained",
        "path": "ServiceRequest.contained",
        "short": "Cannot include any contained resources in the resource as part of the de-identified or anonymized data.",
        "min": 0,
        "max": "0",
        "mustSupport": false
      },
      {
        "id": "ServiceRequest.status",
        "path": "ServiceRequest.status",
        "min": 1,
        "max": "1",
        "mustSupport": true
      },
      {
        "id": "ServiceRequest.intent",
        "path": "ServiceRequest.intent",
        "min": 1,
        "max": "1",
        "mustSupport": true
      },
      {
        "id": "ServiceRequest.doNotPerform",
        "path": "ServiceRequest.doNotPerform",
        "min": 1,
        "max": "1",
        "mustSupport": true
      },
      {
        "id": "ServiceRequest.code",
        "path": "ServiceRequest.code",
        "min": 1,
        "max": "1",
        "mustSupport": true,
        "binding": {
          "strength": "extensible",
          "description": "The set of codes indicating the ServiceRequests",
          "valueSet": "http://hl7.org/fhir/us/core/ValueSet/us-core-procedure-code"
        }
      },
      {
        "id": "ServiceRequest.subject",
        "path": "ServiceRequest.subject",
        "min": 1,
        "max": "1",
        "type": [
          {
            "code": "Reference",
            "targetProfile": [
              "http://hl7.org/fhir/us/dapl/StructureDefinition/dapl-deidentified-patient"
            ]
          }
        ],
        "mustSupport": true
      },
      {
        "id": "ServiceRequest.encounter",
        "path": "ServiceRequest.encounter",
        "min": 0,
        "max": "1",
        "type": [
          {
            "code": "Reference",
            "targetProfile": [
              "http://hl7.org/fhir/us/dapl/StructureDefinition/dapl-deidentified-encounter"
            ]
          }
        ],
        "mustSupport": true
      },
      {
        "id": "ServiceRequest.occurrence[x]",
        "path": "ServiceRequest.occurrence[x]",
        "min": 0,
        "max": "1",
        "mustSupport": true
      },
      {
        "id": "ServiceRequest.authoredOn",
        "path": "ServiceRequest.authoredOn",
        "min": 0,
        "max": "1",
        "mustSupport": true
      },
      {
        "id": "ServiceRequest.requester",
        "path": "ServiceRequest.requester",
        "min": 0,
        "max": "1",
        "mustSupport": true
      },
      {
        "id": "ServiceRequest.bodySite",
        "path": "ServiceRequest.bodySite",
        "min": 0,
        "max": "*",
        "mustSupport": true
      }
    ]
  }
}
