{
  "resourceType": "StructureDefinition",
  "id": "ipa-immunization",
  "extension": [
    {
      "url": "http://hl7.org/fhir/StructureDefinition/structuredefinition-wg",
      "valueCode": "pc"
    },
    {
      "url": "http://hl7.org/fhir/StructureDefinition/structuredefinition-standards-status",
      "valueCode": "trial-use"
    }
  ],
  "url": "http://hl7.org/fhir/uv/ipa/StructureDefinition/ipa-immunization",
  "version": "1.1.0",
  "name": "IPAImmunization",
  "title": "IPA-Immunization",
  "status": "active",
  "experimental": false,
  "date": "2022-08-02",
  "publisher": "HL7 International / Patient Care",
  "contact": [
    {
      "name": "HL7 International / Patient Care",
      "telecom": [
        {
          "system": "url",
          "value": "http://www.hl7.org/Special/committees/patientcare"
        },
        {
          "system": "email",
          "value": "patientcare@lists.HL7.org"
        }
      ]
    }
  ],
  "description": "Minimum expectations for an Immunization resource when accessed via a International Patient Access API",
  "jurisdiction": [
    {
      "coding": [
        {
          "system": "http://unstats.un.org/unsd/methods/m49/m49.htm",
          "code": "001",
          "display": "World"
        }
      ]
    }
  ],
  "copyright": "Used by permission of HL7 International all rights reserved Creative Commons License",
  "fhirVersion": "4.0.1",
  "mapping": [
    {
      "identity": "workflow",
      "uri": "http://hl7.org/fhir/workflow",
      "name": "Workflow Pattern"
    },
    {
      "identity": "v2",
      "uri": "http://hl7.org/v2",
      "name": "HL7 v2 Mapping"
    },
    {
      "identity": "rim",
      "uri": "http://hl7.org/v3",
      "name": "RIM Mapping"
    },
    {
      "identity": "w5",
      "uri": "http://hl7.org/fhir/fivews",
      "name": "FiveWs Pattern Mapping"
    },
    {
      "identity": "cda",
      "uri": "http://hl7.org/v3/cda",
      "name": "CDA (R2)"
    }
  ],
  "kind": "resource",
  "abstract": false,
  "type": "Immunization",
  "baseDefinition": "http://hl7.org/fhir/StructureDefinition/Immunization",
  "derivation": "constraint",
  "differential": {
    "element": [
      {
        "id": "Immunization",
        "path": "Immunization"
      },
      {
        "id": "Immunization.status",
        "extension": [
          {
            "extension": [
              {
                "url": "code",
                "valueCode": "SHALL:populate-if-known"
              },
              {
                "url": "actor",
                "valueCanonical": "http://hl7.org/fhir/uv/ipa/ActorDefinition/server"
              }
            ],
            "url": "http://hl7.org/fhir/StructureDefinition/obligation"
          },
          {
            "extension": [
              {
                "url": "code",
                "valueCode": "SHALL:handle"
              },
              {
                "url": "actor",
                "valueCanonical": "http://hl7.org/fhir/uv/ipa/ActorDefinition/client"
              }
            ],
            "url": "http://hl7.org/fhir/StructureDefinition/obligation"
          }
        ],
        "path": "Immunization.status",
        "min": 1,
        "max": "1",
        "mustSupport": true
      },
      {
        "id": "Immunization.statusReason",
        "path": "Immunization.statusReason",
        "min": 0,
        "max": "1",
        "mustSupport": false
      },
      {
        "id": "Immunization.vaccineCode",
        "extension": [
          {
            "extension": [
              {
                "url": "code",
                "valueCode": "SHALL:populate-if-known"
              },
              {
                "url": "actor",
                "valueCanonical": "http://hl7.org/fhir/uv/ipa/ActorDefinition/server"
              }
            ],
            "url": "http://hl7.org/fhir/StructureDefinition/obligation"
          },
          {
            "extension": [
              {
                "url": "code",
                "valueCode": "SHALL:handle"
              },
              {
                "url": "actor",
                "valueCanonical": "http://hl7.org/fhir/uv/ipa/ActorDefinition/client"
              }
            ],
            "url": "http://hl7.org/fhir/StructureDefinition/obligation"
          }
        ],
        "path": "Immunization.vaccineCode",
        "min": 1,
        "max": "1",
        "mustSupport": true
      },
      {
        "id": "Immunization.patient",
        "extension": [
          {
            "extension": [
              {
                "url": "code",
                "valueCode": "SHALL:populate-if-known"
              },
              {
                "url": "actor",
                "valueCanonical": "http://hl7.org/fhir/uv/ipa/ActorDefinition/server"
              }
            ],
            "url": "http://hl7.org/fhir/StructureDefinition/obligation"
          },
          {
            "extension": [
              {
                "url": "code",
                "valueCode": "SHALL:handle"
              },
              {
                "url": "actor",
                "valueCanonical": "http://hl7.org/fhir/uv/ipa/ActorDefinition/client"
              }
            ],
            "url": "http://hl7.org/fhir/StructureDefinition/obligation"
          }
        ],
        "path": "Immunization.patient",
        "min": 1,
        "max": "1",
        "type": [
          {
            "code": "Reference",
            "targetProfile": [
              "http://hl7.org/fhir/uv/ipa/StructureDefinition/ipa-patient"
            ]
          }
        ],
        "mustSupport": true
      },
      {
        "id": "Immunization.occurrence[x]",
        "extension": [
          {
            "extension": [
              {
                "url": "code",
                "valueCode": "SHALL:populate-if-known"
              },
              {
                "url": "actor",
                "valueCanonical": "http://hl7.org/fhir/uv/ipa/ActorDefinition/server"
              }
            ],
            "url": "http://hl7.org/fhir/StructureDefinition/obligation"
          },
          {
            "extension": [
              {
                "url": "code",
                "valueCode": "SHALL:handle"
              },
              {
                "url": "actor",
                "valueCanonical": "http://hl7.org/fhir/uv/ipa/ActorDefinition/client"
              }
            ],
            "url": "http://hl7.org/fhir/StructureDefinition/obligation"
          }
        ],
        "path": "Immunization.occurrence[x]",
        "min": 1,
        "max": "1",
        "mustSupport": true
      }
    ]
  }
}
